[
  {
    "id": 1,
    "celltype": "水产养殖",
    "agprods": [
      "河蟹",
      "青虾",
      "桂鱼",
      "其他"
    ],
    "desc": "水产养殖塘口"
  },
  {
    "id": 2,
    "celltype": "设施种植",
    "agprods": [
      "茄子",
      "青椒",
      "其他"
    ],
    "desc": "蔬菜种植大棚"
  },
  {
    "id": 3,
    "celltype": "畜禽养殖",
    "agprods": [
      "鸡",
      "鸭",
      "鸽子",
      "其他"
    ],
    "desc": "畜禽养殖车间"
  },
  {
    "id": 4,
    "celltype": "大田种植",
    "agprods": [
      "水稻",
      "小麦",
      "玉米",
      "其他"
    ],
    "desc": "大田种植田块"
  }
]
